README.rst
setup.cfg
setup.py
withenv/__init__.py
withenv/args.py
withenv/cli.py
withenv/config.py
withenv/env.py
withenv/flatten.py
withenv.egg-info/PKG-INFO
withenv.egg-info/SOURCES.txt
withenv.egg-info/dependency_links.txt
withenv.egg-info/entry_points.txt
withenv.egg-info/not-zip-safe
withenv.egg-info/requires.txt
withenv.egg-info/top_level.txt