Metadata-Version: 1.1
Name: withenv
Version: 0.5.1
Summary: Prefix commands with specific environments specified in YAML files.
Home-page: https://github.com/ionrock/withenv
Author: Eric Larson
Author-email: eric@ionrock.org
License: BSD
Keywords: withenv
Platform: UNKNOWN
Classifier: Development Status :: 2 - Pre-Alpha
Classifier: Intended Audience :: Developers
Classifier: License :: OSI Approved :: BSD License
Classifier: Natural Language :: English
Classifier: Programming Language :: Python :: 2
Classifier: Programming Language :: Python :: 2.6
Classifier: Programming Language :: Python :: 2.7
Classifier: Programming Language :: Python :: 3
Classifier: Programming Language :: Python :: 3.3
Classifier: Programming Language :: Python :: 3.4
